{
"media": {
"@ref": "D:\\jianying_template\\N292-春节祝福【兔年春节】-横屏-0分16秒\\videos\\18b44e1ab59e34f5d167638f1416c8e5.jpg",
"track": [
{
"@type": "General",
"ImageCount": "1",
"FileExtension": "jpg",
"Format": "JPEG",
"FileSize": "242785",
"StreamSize": "0",
"File_Created_Date": "UTC 2023-08-17 01:25:06.374",
"File_Created_Date_Local": "2023-08-17 09:25:06.374",
"File_Modified_Date": "UTC 2023-08-17 01:25:06.258",
"File_Modified_Date_Local": "2023-08-17 09:25:06.258"
},
{
"@type": "Image",
"Format": "JPEG",
"Width": "1280",
"Height": "720",
"ColorSpace": "YUV",
"ChromaSubsampling": "4:2:0",
"BitDepth": "8",
"Compression_Mode": "Lossy",
"StreamSize": "242785",
"extra": {
"ColorSpace_ICC": "RGB"
}
}
]
}
}
